Folderesque/__init__.py
Folderesque/__main__.py
Folderesque/config.py
Folderesque/esrgan.py
folderesque-0.1.2.dist-info/METADATA
folderesque-0.1.2.dist-info/WHEEL
folderesque-0.1.2.dist-info/entry_points.txt
folderesque-0.1.2.dist-info/top_level.txt
folderesque-0.1.2.dist-info/RECORD
