Metadata-Version: 2.2
Name: Folderesque
Version: 0.1.2
Summary: Python Script to process and upscale images in specified folders using RRDB models.
Home-page: https://github.com/Sevilze/Folderesque
Requires-Python: >=3.7
Requires-Dist: basicsr==1.4.2
Requires-Dist: numpy==2.2.3
Requires-Dist: opencv_contrib_python==4.10.0.84
Requires-Dist: opencv_python==4.10.0.84
Requires-Dist: opencv_python_headless==4.10.0.84
Requires-Dist: Pillow==11.0.0
Requires-Dist: torch==2.5.1+cu124
Requires-Dist: torchvision==0.20.1+cu124
Requires-Dist: tqdm==4.66.5
Dynamic: description
Dynamic: description-content-type
Dynamic: home-page
Dynamic: requires-dist
Dynamic: requires-python
Dynamic: summary
